adder.v
module AdderWrapper #(
    parameter WORD_WIDTH = 32
) (
    input clk,
    input reset_n,

    input [WORD_WIDTH-1:0] a,
    input [WORD_WIDTH-1:0] b,

    output cout,
    output [WORD_WIDTH-1:0] y
);

// reg cout_reg;
// reg [WORD_WIDTH-1:0] y_reg;

// assign cout = cout_reg;
// assign y = y_reg;

// wire cout_w;
// wire [WORD_WIDTH-1:0] y_w;

Adder #(.WORD_WIDTH(WORD_WIDTH)) adder_unit (
    .a(a), .b(b), .cout(cout), .y(y)
);

// always @(posedge clk or negedge reset_n) begin
//     if (!reset_n) begin
//         cout_reg <= 0;
//         y_reg <= 0;
//     end else begin
//         cout_reg <= cout_w;
//         y_reg <= y_w;
//     end
// end
    
endmodule


module Adder #(
    parameter WORD_WIDTH = 32
) (
    input [WORD_WIDTH-1:0] a,
    input [WORD_WIDTH-1:0] b,

    output cout,
    output [WORD_WIDTH-1:0] y
);

wire [WORD_WIDTH:0] carry;

assign carry[0] = 1'b0;
assign cout = carry[WORD_WIDTH];

genvar witer;

generate
    for (witer = 0; witer < WORD_WIDTH; witer = witer+1) begin: FADDERS
        FullAdder fadd(.a(a[witer]), .b(b[witer]), .Cin(carry[witer]), .s(y[witer]), .Cout(carry[witer+1]));
    end
endgenerate
    
endmodule


module FullAdder (
    input a,
    input b,
    input Cin,

    output s,
    output Cout
);

assign s = a ^ b ^ Cin;
assign Cout = (a & b) | (a & Cin) | (b & Cin);

endmodule

multiplier.v
module MultiplierWrapper #(
    parameter WORD_WIDTH = 8
) (
    input clk,
    input reset_n,

    input [WORD_WIDTH-1:0] a,
    input [WORD_WIDTH-1:0] b,

    output [WORD_WIDTH*2-1:0] y
);

Multiplier #(.WORD_WIDTH(WORD_WIDTH)) mul_unit (
    .a(a), .b(b), .y(y)
);
    
endmodule


module Multiplier #(
    parameter WORD_WIDTH = 8
) (
    input [WORD_WIDTH-1:0] a,
    input [WORD_WIDTH-1:0] b,

    output [WORD_WIDTH*2-1:0] y
);

assign y = a * b;
    
endmodule

processing_element.v
`include "adder.v"
`include "multiplier.v"


module ProcessingElementWS #(
    parameter WORD_WIDTH = 8
) (
    input clk,      // global clock signal
    input reset_n,  // global reset signal

    input [1:0] control,  // control signal (00: IDLE, 01: WEIGHT_INPUT, 10: MULTIPLY)

    input  [WORD_WIDTH-1:0]   a_in,  // activation input port
    input  [WORD_WIDTH*4-1:0] d_in,  // data(weight and partial num) input port

    output [1:0] control_out,  // propagation of control signal to right-adjacent PE

    output [WORD_WIDTH-1:0]   a_out,  // output port for activation propagation to right-adjacent PE
    output [WORD_WIDTH*4-1:0] d_out   // output port for data(weight and partial sum) propatation to bottom-adjacent PE
);

// Registers and output assignment
reg [WORD_WIDTH-1:0]   w_out_reg;   // weight output register
reg [WORD_WIDTH-1:0]   a_out_reg;   // activation output register
reg [WORD_WIDTH*4-1:0] ps_out_reg;  // partial sum output register

reg [1:0] control_out_reg;  // control propagation toward right-adjacent PE

assign a_out = a_out_reg;
assign d_out = (control[1] == 1'b0) ? { {WORD_WIDTH*3{1'b0}}, w_out_reg } : ps_out_reg;

assign control_out = control_out_reg;


// Multiplier Instantiation (weight and activation multiplication)
wire [WORD_WIDTH-1:0] w_val,    // weight value
                      a_val;    // activation value
wire [WORD_WIDTH*2-1:0] y_val;  // weight * activaiton

assign w_val = w_out_reg;
assign a_val = a_in;

Multiplier #(.WORD_WIDTH(WORD_WIDTH)) mul_unit (
    .a(w_val), .b(a_val), .y(y_val)
);


// Adder Instantiation (partial sum accumulation)
wire [WORD_WIDTH*4-1:0] ext_y_val,   // multiplication result extended to INT32 
                        ps_out_val;  // partial sum output value
wire ps_out_cout;  // overflow (unused)

assign ext_y_val = { {WORD_WIDTH*2{1'b0}}, y_val };

Adder #(.WORD_WIDTH(WORD_WIDTH*4)) add_unit (
    .a(ext_y_val), .b(d_in), .y(ps_out_val), .cout(ps_out_cout)
);


// Main operation (proper operation with respect to control signal)
always @(posedge clk or negedge reset_n) begin
    if (!reset_n) begin
        w_out_reg <= 0;
        a_out_reg <= 0;
        ps_out_reg <= 0;

        control_out_reg <= 0;
    end 
    
    else begin
        control_out_reg <= control;

        case (control)
            2'b00: begin  // IDLE
                w_out_reg <= 0;
                a_out_reg <= 0;
                ps_out_reg <= 0;
            end

            2'b01: begin  // WEIGHT INPUT MODE
                w_out_reg <= d_in[WORD_WIDTH-1:0];
                a_out_reg <= 0;
                ps_out_reg <= 0;
            end

            2'b10: begin  // COMPUTATION MODE
                a_out_reg <= a_in;
                ps_out_reg <= ps_out_val;
            end

            default: begin
                w_out_reg <= 0;
                a_out_reg <= 0;
                ps_out_reg <= 0;
            end
        endcase
    end
end
  
endmodule

systolic_array.v
`include "processing_element.v"


module SystolicArrayWS #(
    parameter ARR_WIDTH  = 8,
    parameter ARR_HEIGHT = 8,
    parameter WORD_WIDTH = 8
) (
    input clk,      // global clock signal
    input reset_n,  // global reset signal
    
    input [1:0] control,  // systolic array control signal

    input [WORD_WIDTH*ARR_WIDTH-1:0]  w_in_vec,  // weight input port
    input [WORD_WIDTH*ARR_HEIGHT-1:0] a_in_vec,  // activation input port

    output [WORD_WIDTH*4*ARR_WIDTH-1:0] ps_out_vec  // partial sum output port
);

// Wire split (vector to array)
wire [WORD_WIDTH*4-1:0] w_in   [0:ARR_WIDTH-1];
wire [WORD_WIDTH-1:0]   a_in   [0:ARR_HEIGHT-1];
wire [WORD_WIDTH*4-1:0] ps_out [0:ARR_WIDTH-1];

genvar w_in_idx;
genvar a_in_idx;
genvar ps_out_idx;

generate
    for (w_in_idx = 0; w_in_idx < ARR_WIDTH; w_in_idx = w_in_idx+1) begin
        assign w_in[w_in_idx] = { {WORD_WIDTH*3{1'b0}}, w_in_vec[(w_in_idx+1)*WORD_WIDTH-1:w_in_idx*WORD_WIDTH] };
    end

    for (a_in_idx = 0; a_in_idx < ARR_HEIGHT; a_in_idx = a_in_idx+1) begin
        assign a_in[a_in_idx] = a_in_vec[(a_in_idx+1)*WORD_WIDTH-1:a_in_idx*WORD_WIDTH];
    end

    for (ps_out_idx = 0; ps_out_idx < ARR_WIDTH; ps_out_idx = ps_out_idx+1) begin
        assign ps_out_vec[(ps_out_idx+1)*WORD_WIDTH*4-1:ps_out_idx*WORD_WIDTH*4] = ps_out[ps_out_idx];
    end
endgenerate


// Generate systolic array
wire [WORD_WIDTH-1:0]   a_in_arr [0:ARR_HEIGHT*ARR_WIDTH-1];
wire [WORD_WIDTH*4-1:0] d_in_arr [0:ARR_HEIGHT*ARR_WIDTH-1];

wire [1:0] control_arr [0:ARR_HEIGHT*ARR_WIDTH-1];
wire [1:0] control_out_arr [0:ARR_HEIGHT*ARR_WIDTH-1];

wire [WORD_WIDTH-1:0]   a_out_arr [0:ARR_HEIGHT*ARR_WIDTH-1];
wire [WORD_WIDTH*4-1:0] d_out_arr [0:ARR_HEIGHT*ARR_WIDTH-1];

genvar pe_idx;
genvar ro_idx;
genvar co_idx;

generate
    for (pe_idx = 0; pe_idx < ARR_HEIGHT*ARR_WIDTH; pe_idx = pe_idx+1) begin
        ProcessingElementWS #(
            .WORD_WIDTH(WORD_WIDTH)
        ) pe_unit (
            .clk(clk), .reset_n(reset_n),
            .control(control_arr[pe_idx]),
            .a_in(a_in_arr[pe_idx]), .d_in(d_in_arr[pe_idx]),
            .control_out(control_out_arr[pe_idx]),
            .a_out(a_out_arr[pe_idx]), .d_out(d_out_arr[pe_idx])
        );
    end

    for (ro_idx = 0; ro_idx < ARR_HEIGHT-1; ro_idx = ro_idx+1) begin
        for (co_idx = 0; co_idx < ARR_WIDTH; co_idx = co_idx+1) begin
            assign a_in_arr[(ro_idx+1)*ARR_WIDTH+co_idx] = a_out_arr[ro_idx*ARR_WIDTH+co_idx];
        end
    end

    for (co_idx = 0; co_idx < ARR_WIDTH-1; co_idx = co_idx+1) begin
        for (ro_idx = 0; ro_idx < ARR_HEIGHT; ro_idx = ro_idx+1) begin
            assign d_in_arr[ro_idx*ARR_WIDTH+co_idx+1] = d_out_arr[ro_idx*ARR_WIDTH+co_idx];
            assign control_arr[ro_idx*ARR_WIDTH+co_idx+1] = control_out_arr[ro_idx*ARR_WIDTH+co_idx];
        end
    end

    for (co_idx = 0; co_idx < ARR_WIDTH; co_idx = co_idx+1) begin
        assign d_in_arr[co_idx] = w_in[co_idx];
        assign ps_out[co_idx] = d_out_arr[(ARR_HEIGHT-1)*ARR_WIDTH+co_idx];
    end

    for (ro_idx = 0; ro_idx < ARR_HEIGHT-1; ro_idx = ro_idx+1) begin
        assign control_arr[ARR_WIDTH*(ro_idx+1)] = control_out_arr[ARR_WIDTH*ro_idx];
    end

    for (ro_idx = 0; ro_idx < ARR_HEIGHT; ro_idx = ro_idx+1) begin
        assign a_in_arr[ARR_WIDTH*ro_idx] = a_in[ro_idx];
    end
endgenerate

assign control_arr[0] = control;
    
endmodule

testbenches/systolic_array_ws_tb.v
`include "systolic_array.v"

`timescale 1ns/1ps

module systolic_array_tb;

parameter  CLOCK_PS = 10000;
localparam HCLOCK_PS = CLOCK_PS / 2;

localparam ARR_WIDTH = 4;
localparam ARR_HEIGHT = 4;
localparam WORD_WIDTH = 8;

integer clk_count;

reg clk;
reg reset_n;

// Instantiation of processing element
reg [1:0] control;

wire [WORD_WIDTH*ARR_WIDTH-1:0] w_in_vec;
wire [WORD_WIDTH*ARR_HEIGHT-1:0] a_in_vec;

wire [WORD_WIDTH*4*ARR_WIDTH-1:0] ps_out_vec;

SystolicArrayWS #(
    .ARR_WIDTH(ARR_WIDTH), .ARR_HEIGHT(ARR_HEIGHT), .WORD_WIDTH(WORD_WIDTH)
) sa_unit (
    .clk(clk), .reset_n(reset_n),
    .control(control),
    .w_in_vec(w_in_vec), .a_in_vec(a_in_vec),
    .ps_out_vec(ps_out_vec)
);


// Wire split (vector to array)
reg [WORD_WIDTH-1:0] w_in [0:ARR_WIDTH-1];
reg [WORD_WIDTH-1:0] a_in [0:ARR_HEIGHT-1];
wire [WORD_WIDTH*4-1:0] ps_out [0:ARR_WIDTH-1];

genvar w_in_idx;
genvar a_in_idx;
genvar ps_out_idx;

generate
    for (w_in_idx = 0; w_in_idx < ARR_WIDTH; w_in_idx = w_in_idx+1) begin
        assign w_in_vec[WORD_WIDTH*(w_in_idx+1)-1:WORD_WIDTH*w_in_idx] = w_in[w_in_idx];
    end

    for (a_in_idx = 0; a_in_idx < ARR_HEIGHT; a_in_idx = a_in_idx+1) begin
        assign a_in_vec[WORD_WIDTH*(a_in_idx+1)-1:WORD_WIDTH*a_in_idx] = a_in[a_in_idx];
    end

    for (ps_out_idx = 0; ps_out_idx < ARR_WIDTH; ps_out_idx = ps_out_idx+1) begin
        assign ps_out[ps_out_idx] = ps_out_vec[(ps_out_idx+1)*WORD_WIDTH*4-1:ps_out_idx*WORD_WIDTH*4];
    end
endgenerate


// Clock signal generation
initial begin : CLOCK_GENERATOR
    clk = 1'b0;
    clk_count = 0;
    forever
        # HCLOCK_PS clk = ~clk;
end

always @(posedge clk) begin
    clk_count  = clk_count + 1;
end


// PE test
initial begin : PE_TEST
    $dumpfile("systolic_array_ws_tb.vcd");
    
    $dumpvars(-1, clk);
    $dumpvars(-1, reset_n);
    $dumpvars(-1, control);

    for (integer ridx = 0; ridx < ARR_HEIGHT; ridx = ridx+1) begin
        $dumpvars(-1, a_in[ridx]);
    end

    for (integer cidx = 0; cidx < ARR_WIDTH; cidx = cidx+1) begin
        $dumpvars(-1, w_in[cidx]);
        $dumpvars(-1, ps_out[cidx]);
    end

    $monitor("clk: %2d   control: %b ", clk_count, control);

    reset_n = 1;
    # HCLOCK_PS

    reset_n = 0;
    # HCLOCK_PS

    reset_n = 1;
    control = 2'b00;

    # CLOCK_PS

    control = 2'b01;

    w_in[0] = 1;
    w_in[1] = 2;
    w_in[2] = 3;
    w_in[3] = 4;
    # CLOCK_PS

    w_in[0] = 4;
    w_in[1] = 3;
    w_in[2] = 2;
    w_in[3] = 1;
    # CLOCK_PS

    w_in[0] = 1;
    w_in[1] = 3;
    w_in[2] = 2;
    w_in[3] = 4;
    # CLOCK_PS

    w_in[0] = 4;
    w_in[1] = 2;
    w_in[2] = 1;
    w_in[3] = 3;
    # CLOCK_PS

    control = 2'b10;

    a_in[0] = 1;
    a_in[1] = 2;
    a_in[2] = 3;
    a_in[3] = 4;
    # CLOCK_PS

    a_in[0] = 4;
    a_in[1] = 3;
    a_in[2] = 2;
    a_in[3] = 1;
    # CLOCK_PS

    a_in[0] = 1;
    a_in[1] = 3;
    a_in[2] = 2;
    a_in[3] = 4;
    # CLOCK_PS

    a_in[0] = 4;
    a_in[1] = 2;
    a_in[2] = 1;
    a_in[3] = 3;
    # CLOCK_PS

    # CLOCK_PS
    # CLOCK_PS
    # CLOCK_PS
    # CLOCK_PS
    # CLOCK_PS
    # CLOCK_PS
    # CLOCK_PS
    # CLOCK_PS
    # CLOCK_PS
    # CLOCK_PS
    # CLOCK_PS

    $finish;
end

    
endmodule

testbenches/systolic_array_ws_tb.vcd
$date
	Tue Dec 13 17:03:40 2022
$end
$version
	Icarus Verilog
$end
$timescale
	1ps
$end
$scope module systolic_array_tb $end
$var reg 1 ! clk $end
$upscope $end
$scope module systolic_array_tb $end
$var reg 1 " reset_n $end
$upscope $end
$scope module systolic_array_tb $end
$var reg 2 # control [1:0] $end
$upscope $end
$scope module systolic_array_tb $end
$var reg 8 $ \a_in[0] [7:0] $end
$upscope $end
$scope module systolic_array_tb $end
$var reg 8 % \a_in[1] [7:0] $end
$upscope $end
$scope module systolic_array_tb $end
$var reg 8 & \a_in[2] [7:0] $end
$upscope $end
$scope module systolic_array_tb $end
$var reg 8 ' \a_in[3] [7:0] $end
$upscope $end
$scope module systolic_array_tb $end
$var reg 8 ( \w_in[0] [7:0] $end
$upscope $end
$scope module systolic_array_tb $end
$var reg 32 ) \ps_out[0] [31:0] $end
$upscope $end
$scope module systolic_array_tb $end
$var reg 8 * \w_in[1] [7:0] $end
$upscope $end
$scope module systolic_array_tb $end
$var reg 32 + \ps_out[1] [31:0] $end
$upscope $end
$scope module systolic_array_tb $end
$var reg 8 , \w_in[2] [7:0] $end
$upscope $end
$scope module systolic_array_tb $end
$var reg 32 - \ps_out[2] [31:0] $end
$upscope $end
$scope module systolic_array_tb $end
$var reg 8 . \w_in[3] [7:0] $end
$upscope $end
$scope module systolic_array_tb $end
$var reg 32 / \ps_out[3] [31:0] $end
$upscope $end
$enddefinitions $end
$comment Show the parameter values. $end
$dumpall
$end
#0
$dumpvars
bx /
bx .
bx -
bx ,
bx +
bx *
bx )
bx (
bx '
bx &
bx %
bx $
bx #
1"
0!
$end
#5000000
b0 )
b0 +
b0 -
b0 /
0"
1!
#10000000
b0 #
1"
0!
#15000000
1!
#20000000
0!
b100 .
b11 ,
b10 *
b1 (
b1 #
#25000000
1!
#30000000
0!
b1 .
b10 ,
b11 *
b100 (
#35000000
1!
#40000000
0!
b100 .
b10 ,
b11 *
b1 (
#45000000
1!
#50000000
0!
b11 .
b1 ,
b10 *
b100 (
#55000000
b100 /
b11 -
b10 +
b1 )
1!
#60000000
0!
b100 '
b11 &
b10 %
b1 $
b10 #
#65000000
b1000 )
b11 +
b10 -
b1 /
1!
#70000000
0!
b1 '
b10 &
b11 %
b100 $
#75000000
b100 /
b1011 +
b1110 )
1!
#80000000
0!
b100 '
b10 &
b11 %
b1 $
#85000000
b10010 )
b1101 +
b1101 -
b11 /
1!
#90000000
0!
b11 '
b1 &
b10 %
b100 $
#95000000
b10011 /
b1010 -
b10110 +
b10110 )
1!
#100000000
0!
#105000000
b11110 )
b11001 +
b10101 -
b1010 /
1!
#110000000
0!
#115000000
b11101 /
b11100 +
b10001 )
1!
#120000000
0!
#125000000
b11101 )
b10011 +
b10110 -
b100000 /
1!
#130000000
0!
#135000000
b101000 /
b10001 -
b11001 +
1!
#140000000
0!
#145000000
b10100 -
b11011 /
1!
#150000000
0!
#155000000
b100100 /
1!
