params.v
/*
 * Mode of Processing Elements
 * 
 * Params
 *   1) PEMODE_WL: Mode for weight load
 *   2) PEMODE_PS: Mode for partial sum
 */

localparam PEMODE_WL = 1'b0;
localparam PEMODE_PS = 1'b1;

processing_element.v
/*
 * Processing Element with Weight Stationary Dataflow
 *
 * Description
 *   Weight stationary processing element for systolic array
 *   For simplicity, this processor only utilizes integer values 
 *   (weight and input feature values)
 */

module ProcessingElementWS #(
    parameter WORDWIDTH = 8  // dtype: int8
) (
    input clk,      // clock signal
    input reset_n,  // reset signal
    input mode,     // current mode (weight load mode or partial sum computation mode)

    input  [WORDWIDTH:0]   w_in,
    input  [WORDWIDTH:0]   a_in,

    output [WORDWIDTH:0]   a_out,
    output [WORDWIDTH*4:0] ps_out
);

`include "./params.v"

reg [WORDWIDTH:0]   weight;
reg [WORDWIDTH:0]   activation;
reg [WORDWIDTH*4:0] partial_sum;

assign a_out = activation;
assign ps_out = partial_sum;

always @(posedge clk or negedge reset_n) begin : PSUM_CALC
    if (reset_n == 1'b0) begin
        weight <= 0;
        activation <= 0;
        partial_sum <= 0;
    end else begin
        if (mode == PEMODE_WL) begin
            weight <= w_in;
        end

        else if (mode == PEMODE_PS) begin
            activation <= a_in;
            partial_sum <= partial_sum + (weight * a_in);
        end
    end
end
    
endmodule

tb_processing_element.v
`include "processing_element.v"

`timescale 1ns/1ps


/*
 * Testbench for Weight Stationary Processing Element
 *
 * Description
 *   Weight stationary processing element for systolic array
 *   For simplicity, this processor only utilizes integer values 
 *   (weight and input feature values)
 */

module tb_processing_element;

// Params
`include "./params.v"

parameter  CLOCK_PS = 10000;
localparam HCLOCK_PS = CLOCK_PS / 2;
localparam WORDWIDTH = 8;


// Instantiation of processing element
reg clk;
reg reset_n;
reg mode;

reg [WORDWIDTH:0]    w_in;
reg [WORDWIDTH:0]    a_in;

wire [WORDWIDTH:0]   a_out;
wire [WORDWIDTH*4:0] ps_out;

ProcessingElementWS #(
    .WORDWIDTH(WORDWIDTH)
) pe (
    .clk(clk),
    .reset_n(reset_n),
    .mode(mode),

    .w_in(w_in),
    .a_in(a_in),

    .a_out(a_out),
    .ps_out(ps_out)
);


// Clock signal generation
initial begin : CLOCK_GENERATOR
    clk = 1'b0;
    forever
        # HCLOCK_PS clk = ~clk;
end


// PE test
initial begin : PE_TEST
    $dumpfile("tb_processing_element.vcd");
    $dumpvars(-1, pe);
    $monitor("a_out:  %d\n", a_out);
    $monitor("ps_out: %d\n", ps_out);

    w_in = 3;
    a_in = 2;

    reset_n = 1;
    # HCLOCK_PS
    reset_n = 0;
    # HCLOCK_PS

    reset_n = 1;
    mode = 1'b0;
    # CLOCK_PS

    mode = 1'b1;
    # CLOCK_PS
    # CLOCK_PS
    # CLOCK_PS
    # CLOCK_PS
    # CLOCK_PS

    $finish;
end

    
endmodule

tb_processing_element.vcd
$date
	Sat Sep 03 21:20:51 2022
$end
$version
	Icarus Verilog
$end
$timescale
	1ps
$end
$scope module tb_processing_element $end
$scope module pe $end
$var wire 9 ! a_in [8:0] $end
$var wire 9 " a_out [8:0] $end
$var wire 1 # clk $end
$var wire 1 $ mode $end
$var wire 33 % ps_out [32:0] $end
$var wire 1 & reset_n $end
$var wire 9 ' w_in [8:0] $end
$var parameter 1 ( PEMODE_PS $end
$var parameter 1 ) PEMODE_WL $end
$var parameter 32 * WORDWIDTH $end
$var reg 9 + activation [8:0] $end
$var reg 33 , partial_sum [32:0] $end
$var reg 9 - weight [8:0] $end
$scope begin PSUM_CALC $end
$upscope $end
$upscope $end
$upscope $end
$enddefinitions $end
$comment Show the parameter values. $end
$dumpall
b1000 *
0)
1(
$end
#0
$dumpvars
bx -
bx ,
bx +
b11 '
1&
bx %
x$
0#
bx "
b10 !
$end
#5000000
b0 %
b0 ,
b0 "
b0 +
b0 -
0&
1#
#10000000
0$
1&
0#
#15000000
b11 -
1#
#20000000
0#
1$
#25000000
b110 %
b110 ,
b10 "
b10 +
1#
#30000000
0#
#35000000
b1100 %
b1100 ,
1#
#40000000
0#
#45000000
b10010 %
b10010 ,
1#
#50000000
0#
#55000000
b11000 %
b11000 ,
1#
#60000000
0#
#65000000
b11110 %
b11110 ,
1#
